aissist/__init__.py
aissist/aissist.py
aissist/code_formatter.py
aissist/config.py
aissist/exceptions.py
aissist/model.py
aissist/prompts.py
aissist/spinner.py
aissist/version.py
aissist-0.1.0.dist-info/entry_points.txt
aissist-0.1.0.dist-info/LICENSE
aissist-0.1.0.dist-info/WHEEL
aissist-0.1.0.dist-info/METADATA
aissist-0.1.0.dist-info/RECORD
