Metadata-Version: 2.1
Name: aissist
Version: 0.1.0
Summary: A simple GPT command line chat interface
Author-email: Craig Booth <craigmbooth@gmail.com>
Requires-Python: >=3.7
Classifier: Development Status :: 4 - Beta
Classifier: Intended Audience :: Developers
Classifier: License :: OSI Approved :: Apache Software License
Classifier: Programming Language :: Python :: 3 :: Only
Classifier: Topic :: Scientific/Engineering :: Artificial Intelligence
Requires-Dist: importlib_metadata<7
Requires-Dist: openai<1
Requires-Dist: prompt_toolkit<4
Requires-Dist: pygments<3
Requires-Dist: retry<1
Requires-Dist: tiktoken<1
Requires-Dist: tomlkit<1
Project-URL: Bug Tracker, https://github.com/craigmbooth/aissist/issues
Project-URL: Homepage, https://github.com/craigmbooth/aissist
